mindaugas_printer/__init__.py
mindaugas_printer/main.py
mindaugas_printer-0.0.1.dist-info/METADATA
mindaugas_printer-0.0.1.dist-info/WHEEL
mindaugas_printer-0.0.1.dist-info/top_level.txt
mindaugas_printer-0.0.1.dist-info/RECORD
