Metadata-Version: 2.1
Name: mindaugas_printer
Version: 0.0.1
Summary: For generating A E S T H E T I C ascii art
Home-page: https://github.com/MindaugasBernatavicius/notes
Author: Mindaugas Bernatavicius
Author-email: testtest2@gmail.com
Classifier: Programming Language :: Python :: 3
Classifier: License :: OSI Approved :: MIT License
Classifier: Operating System :: OS Independent
Requires-Python: >=3.8
